[
    {
        "question": "Q: 어떤 내용의 정책이고, 어떤 목적으로 진행되는지 알려줄 수 있을까요?",
        "passage": "지원내용: 청소년, 청년 창업프로젝트 진행 및 지역사회 문화공유 네트워크 구축\n"
    },
    {
        "question": "Q: 마을에서 활동하는 청년들을 위한 공유플랫폼에 신청하려면 어떤 절차를 거쳐야 하나요?",
        "passage": "제목: 마을청년 공유플랫폼\n신청 절차: 홈페이지 공고 참고하여 온라인 신청\n심사 및 발표: 면접심사\n신청 사이트: https://www.snyouth.or.kr\n제출 서류: 신청서\n"
    },
    {
        "question": "Q: 성남시에 거주하고 있는 20세 청년이 참여할 수 있는 마을청년 공유플랫폼이 있을까요?",
        "passage": "제목: 마을청년 공유플랫폼\n연령: 만 15세 ~ 34세\n거주지 및 소득: 제한없음\n학력: 제한없음\n전공: 제한없음\n취업 상태: 제한없음\n특화 분야: 제한없음\n추가 단서 사항: 성남시 거주, 활동, 재학, 재직 중인 청년\n참여 제한 대상: 정부 및 지자체 사업 참여 제한 중인 자\n"
    },
    {
        "question": "Q: 2023년 상반기에 마을청년 공유플랫폼에 지원할 수 있는 기간은 언제부터 언제까지인가요?",
        "passage": "제목: 마을청년 공유플랫폼\n정책 번호: R2023060213049\n정책 분야: 일자리분야\n지원 내용: 창업프로젝트 지원 등\n사업 운영 기간: 2023.1.1.-2023.12.31.\n사업 신청 기간: 2023년 01월  16일 ~ 2023년 02월  01일\n지원 규모(명): 20건\n비고: 상반기:  2023. 1. 16.(월) ~ 2. 1.(수) 11시 59분\n하반기: 미정\n"
    }
]