[
    {
        "question": "Q: 청년 농업인들에게 어떤 지원이 제공되는지 알려주세요.",
        "passage": "지원내용: 청년 농업인에게 창업자금, 기수.경영 교육과 컨설팅  지원\n"
    },
    {
        "question": "Q: 청년농업인 영농정착 지원을 받기 위해 어떤 절차를 거쳐야 할까요?",
        "passage": "제목: 청년농업인 영농정착 지원\n신청 절차: 온라인신청\n"
    },
    {
        "question": "Q: 청년농업인 영농정착 지원 정책은 어떤 대상을 위해 제공되는지 알려주세요.",
        "passage": "제목: 청년농업인 영농정착 지원\n연령: 만 18세 ~ 40세\n거주지 및 소득: 18세-40세 미만 관내 청년\n학력: 제한없음\n전공: 제한없음\n취업 상태: 제한없음\n특화 분야: 제한없음\n참여 제한 대상: 연령, 주소\n"
    },
    {
        "question": "Q: 청년농업인을 위한 영농정착지원 정책은 어떤 내용을 포함하고 있나요?",
        "passage": "제목: 청년농업인 영농정착 지원\n정책 번호: R2023060213561\n정책 분야: 주거분야\n지원 내용: 영농정착지원금 지급 및 기술 경영 교육\n사업 운영 기간: 1월 접수, 3~12월 집행\n사업 신청 기간: 미정\n비고: 미정\n"
    }
]