[
    {
        "question": "Q: 어떤 프로젝트가 선정되면 사업비를 지원받을 수 있는 정책이 있나요?",
        "passage": "지원내용: 청년문제를 청년 주도로 해결할 수 있는 활동기반 및 청년 네트워크 활성화에 기여, 청년권익증진을 위한 아이디어 프로젝트 공모후 선정팀별 프로젝트 사업비 지원\n"
    },
    {
        "question": "Q: 고양시 청년들을 위한 희망뉴딜 프로젝트 공모사업에 신청하기 위해 어떤 절차를 거쳐야 하나요?",
        "passage": "제목: 고양 청년 희망뉴딜 프로젝트 공모사업\n신청 절차: 신청서류 작성 후 방문 또는 이메일 접수\n심사 및 발표: 사업심사 후 선정\n신청 사이트: https://www.goyang.go.kr/www/index.do\n"
    },
    {
        "question": "Q: 고양시에 거주하고 있는 25세 청년들끼리 비영리단체를 만들어서 참여할 수 있는 정책 프로젝트가 있을까요?",
        "passage": "제목: 고양 청년 희망뉴딜 프로젝트 공모사업\n연령: 만 18세 ~ 39세\n거주지 및 소득: 고양시에서 거주하거나 활동하는 만 18세-39세 청년 3인 이상으로 구성된 비영리단체 또는 모임\n학력: 제한없음\n전공: 제한없음\n취업 상태: 제한없음\n특화 분야: 제한없음\n"
    },
    {
        "question": "Q: 고양시 청년들이 청년정책 아이디어를 실현하기 위해 지원받을 수 있는 프로젝트는 어떤 것이 있나요?",
        "passage": "제목: 고양 청년 희망뉴딜 프로젝트 공모사업\n정책 번호: R2023060213090\n정책 분야: 참여.권리분야\n지원 내용: 청년정책 아이디어 실현 프로젝트 사업비 지원(팀별 5백만원 이내)\n사업 운영 기간: 2023. 2. - 2023. 12.\n사업 신청 기간: 상시\n지원 규모(명): 4개팀 이상(예산범위 내, 20,000천원)\n비고: 참고: 22년의 경우) 2022. 2.\n"
    }
]