[
    {
        "question": "Q: 청년인증기업을 위해 어떤 지원이 제공되는지 알려주세요.",
        "passage": "지원내용: 청년인증기업에 대한 자금, 마케팅지원 및 기술지원 연계\n"
    },
    {
        "question": "Q: 청년기업 인증을 받기 위해 필요한 서류는 무엇인가요?",
        "passage": "제목: 청년기업 인증 지원사업\n신청 절차: 방문 또는 우편접수(김포시청 기업지원과 기업지원팀)\n심사 및 발표: 1차 서류심사\n2차 현장실사\n제출 서류: - 청년기업 인증(변경) 신청서 [서식 1]\n- 사업자등록증 1부\n- 신분증 사본 1부\n- 법인등기부등본 1부(법인의 경우)\n- 국세·지방세 납세증명서 각 1부\n- 기업(개인)정보 수집이용 동의서 [서식 2]\n"
    },
    {
        "question": "Q: 어떤 조건을 만족하는 기업이 청년기업 인증 지원사업을 받을 수 있을까요?",
        "passage": "제목: 청년기업 인증 지원사업\n연령: 만 19세 ~ 39세\n거주지 및 소득: 관내에 소재(본사 또는 주공장) 한 기업 중소기업기본법 시행령 제3조제1항에 의한 중소기업 중 19세 이상 39세 이하의 청년이 대표로 있는 기업\n학력: 제한없음\n전공: 제한없음\n취업 상태: (예비)창업자(기업대표)\n특화 분야: 제한없음\n추가 단서 사항: 유효기간 : 3년 ( ※ 만료전 유효기간 연장 후 재인증 가능)\n"
    },
    {
        "question": "Q: 청년기업 인증을 받은 업체들에게 어떤 지원이 제공되는지 알려주세요.",
        "passage": "제목: 청년기업 인증 지원사업\n정책 번호: R2023060212957\n정책 분야: 일자리분야\n지원 내용: 연관 자금지원- 중소기업, 소상공인 운전자금 이자차액(0.5% 추가보전)\n마케팅지원, 기업애로 해소지원, 기술지원, 현장 행정 및 간담회 실시\n사업 운영 기간: 2023.01~2023.12\n사업 신청 기간: 상시\n지원 규모(명): 청년기업 인증 받은 업체\n비고: 연중\n"
    }
]