[
    {
        "question": "Q: 어떤 지원을 위한 청년 플랫폼 공간이 제공되고 있는지 알려주세요.",
        "passage": "지원내용: 청년의 소통, 취업 및 창업지원, 문화활동 공유 등 다양한 청년활동지원을 위한 청년 플랫폼 공간\n"
    },
    {
        "question": "Q: 성남시 청년지원센터 운영 및 활성화에 신청하는 방법은 무엇인가요?",
        "passage": "제목: 성남시 청년지원센터 운영 및 활성화\n신청 절차: 성남시 청년지원센터 청년이봄 홈페이지 신청 또는 유선연락(070-4908-2090)\n- 홈페이지 또는 카카오톡 플러스친구(성남시 청년지원센터 청년이봄)\n심사 및 발표: 제한없음\n신청 사이트: https://snspring.or.kr\n"
    },
    {
        "question": "Q: 성남시에 거주하는 청년들은 어떤 지원을 받을 수 있을까요?",
        "passage": "제목: 성남시 청년지원센터 운영 및 활성화\n연령: 만 19세 ~ 34세\n거주지 및 소득: 성남시 청년 누구나\n학력: 제한없음\n전공: 제한없음\n취업 상태: 제한없음\n특화 분야: 제한없음\n추가 단서 사항: 제한없음\n참여 제한 대상: 제한없음\n"
    },
    {
        "question": "Q: 성남시 청년지원센터에서 제공하는 프로그램을 이용하려면 어떻게 신청해야 하나요?",
        "passage": "제목: 성남시 청년지원센터 운영 및 활성화\n정책 번호: R2023060213022\n정책 분야: 복지.문화분야\n지원 내용: 1. 청년 박람회, 공모전, 청년정책 일정 등에 대한 정보 제공\n2. 청년 커뮤니티센터, 공유부엌, 세미나실, 창업공간 및 프로그램 지원\n사업 운영 기간: 2023.1.1.-2023.12.31.\n사업 신청 기간: 상시\n지원 규모(명): 1일 평균 28명 이용\n비고: 운영시간(월-금 10시부터 21시까지, 토 10시부터 15시까지)\n"
    }
]