[
    {
        "question": "Q: 어려움을 겪고 있는 청년들을 위해 면접시 필요한 정장을 무료로 대여하는 정책은 어디에서 받을 수 있을까요?",
        "passage": "지원내용: 면접역량과 시선, 음성수준 등을 상세하게 분석한 결과와 녹화영상을 제공 받고 구직활동으로 어려움을 겪고 있는 청년들에게 면접시 필요한 정장을  무료로 대여하여 취업비용 부담 해소 및 취업에 성공할 수 있도록 지원\n"
    },
    {
        "question": "Q: AI 모의면접서비스 및 청년날개 면접정장 무료대여사업에 신청하기 위해 필요한 서류는 무엇인가요?",
        "passage": "제목: AI 모의면접서비스 및 청년날개 면접정장 무료대여사업\n신청 절차: 공고문 확인\n신청 사이트: AI모의면접 서비스: https://www.gunpo.go.kr/www/index.do\n청년날개 면접정장 무료대여: https://apply.jobaba.net/bsns/bsnsListView.do\n제출 서류: 공고문 확인\n"
    },
    {
        "question": "Q: 군포시에 거주하고 있는 25세 대학 졸업 예정자인데, 무직 상태에서도 지원받을 수 있는 AI 모의면접서비스 및 청년날개 면접정장 무료대여사업이 있을까요?",
        "passage": "제목: AI 모의면접서비스 및 청년날개 면접정장 무료대여사업\n연령: 만 18세 ~ 39세\n거주지 및 소득: 군포시 거주 구직 청년(관내 고등학교·대학교 졸업예정자 및 졸업생 포함)\n학력: 제한없음\n전공: 제한없음\n취업 상태: 미취업자\n특화 분야: 제한없음\n"
    },
    {
        "question": "Q: 청년들을 위한 AI 모의면접서비스와 면접정장 무료대여 사업은 어떤 내용을 포함하고 있나요?",
        "passage": "제목: AI 모의면접서비스 및 청년날개 면접정장 무료대여사업\n정책 번호: R2023060213159\n정책 분야: 교육분야\n지원 내용: 1. 청년 본인이 직접 모의 면접 후 분석결과 확인\n2. 면접정장 대여\n- (남자) 재킷, 바지, 셔츠, 구두, 벨트, 넥타이\n- (여자) 재킷, 스커트, 블라우스, 구두\n사업 운영 기간: 2023.01.01.-2023.12.31.\n사업 신청 기간: 미정\n지원 규모(명): 예산 소진시까지\n"
    }
]