[
    {
        "question": "Q: 어떤 정책이 청년들이 스스로 기획하고 실행하는 청년주도의 축제 개최를 지원해주나요?",
        "passage": "지원내용: 청년 스스로 축제 주인공이 되어 직접 기획하고 실행하는 청년주도의 축제 개최\n"
    },
    {
        "question": "Q: 도봉청년축제는 어떤 내용으로 진행되는 행사인가요?",
        "passage": "제목: 도봉청년축제\n"
    },
    {
        "question": "Q: 도봉구에 거주하는 25세 청년이 참여할 수 있는 도봉청년축제가 있을까요?",
        "passage": "제목: 도봉청년축제\n연령: 만 19세 ~ 39세\n거주지 및 소득: 도봉구 청년 등\n학력: 제한없음\n전공: 제한없음\n취업 상태: 제한없음\n특화 분야: 제한없음\n"
    },
    {
        "question": "Q: 도봉구에 거주하는 청년들을 위한 청년축제가 있나요?",
        "passage": "제목: 도봉청년축제\n정책 번호: R2023050912403\n정책 분야: 복지.문화분야\n지원 내용: 토크콘서트, 문화공연, 부스운영 지원\n사업 운영 기간: 2023.5. ~ 10.\n사업 신청 기간: 미정\n지원 규모(명): 500명\n비고: 2023.9. 예정\n"
    }
]