[
    {
        "question": "Q: 어떤 목적으로 외식기반창업을 지원하는 정책이 있을까요?",
        "passage": "지원내용: 외식기반창업을 목적으로, 공유주방 중심의 청년창업활동 및 교육, 커뮤니티 지원\n"
    },
    {
        "question": "Q: 어떤 정책이 청년들의 삶을 발전시키기 위해 운영되고 있을까요?",
        "passage": "제목: 청년살이발전소 운영\n"
    },
    {
        "question": "Q: 청년살이발전소 운영 정책은 어떤 연령대를 대상으로 하고 있나요?",
        "passage": "제목: 청년살이발전소 운영\n연령: 만 19세 ~ 39세\n거주지 및 소득: 만 19세~39세 미취업 청년\n학력: 제한없음\n전공: 제한없음\n취업 상태: 제한없음\n특화 분야: 제한없음\n"
    },
    {
        "question": "Q: 청년들을 위한 청년살이발전소에서 제공하는 지원 내용은 무엇인가요?",
        "passage": "제목: 청년살이발전소 운영\n정책 번호: R2023050912467\n정책 분야: 일자리분야\n지원 내용: 청년진로탐색, 커뮤니티 활성화, 지역문화 탐색 등\n사업 운영 기간: 2023.01.01.~2023.12.31.\n사업 신청 기간: 미정\n지원 규모(명): 100명\n비고: 2023.2.~12.\n"
    }
]